Workbook

Sheet Cover
B9: Jersey Mike's Subs
B11: Buyout Model
B13: =TODAY() -> 46209
B15: By: Tyler Spencer
B18: SPONSOR RETURNS
B20: Scenario | C20: MOIC | D20: IRR
B21: Best Case (Bull) | C21: ='LBO Exit'!G23 -> 1.9994057 | D21: ='LBO Exit'!H23 -> 0.50166718
B22: Base Case | C22: ='LBO Exit'!G20 -> 1.7894943 | D22: ='LBO Exit'!H20 -> 0.40703979
B23: Worst Case (Bear) | C23: ='LBO Exit'!G17 -> 1.579583 | D23: ='LBO Exit'!H17 -> 0.3076997

Sheet Assumptions & Financials
B2: =Cover!B9 -> Jersey Mike's Subs
B3: Assumptions & Financials
B4: ($ Millions)
B6: Transaction Assumptions
B8: Entry Enterprise Value | E8: 8000
B9: Entry LTM EBITDA | E9: 263
B10: Entry Close Date | E10: 45673
B11: Net Debt at Entry | E11: 1750
B12: Exit Enterprise Value | E12: 12000
B13: Exit EBITDA Multiple | E13: 31
B14: Exit Close Date | E14: 46295
B15: Net Debt at Exit | E15: 2100
B16: Founder Equity | E16: 0.1
B17: Transaction Fees | E17: 0.015
B19: Company Financials
E20: 2024A | F20: 2025A | G20: Q1 2026A
B22: Revenue | E22: 653 | F22: =696+28 -> 724 | G22: 185
B23: Selling, General, & Administrative | E23: -349 | F23: =-(214+19) -> -233 | G23: -78
B24: Advertising Expense | E24: -220 | F24: =-(207+8) -> -215 | G24: -61
B25: Depreciation & Amortization | E25: -10 | F25: =-(96+0) -> -96 | G25: -26
B26: Company-owned stores expenses | E26: -30 | F26: =-(28+1) -> -29 | G26: -8
B27: EBIT | E27: =SUM(E22:E26) -> 44 | F27: =SUM(F22:F26) -> 151 | G27: =SUM(G22:G26) -> 12
B29: Interest Income (Expense) | E29: -38 | F29: =(9-99)+(1-5) -> -94 | G29: =1-30 -> -29
B30: EBT | E30: =E27+E29 -> 6 | F30: =F27+F29 -> 57 | G30: =G27+G29-7 -> -24
B32: Other Expense | E32: 0 | F32: -1 | G32: 0
B33: Income Tax Expense | E33: -1 | F33: -1 | G33: 0
B34: Net Income | E34: =E30+E33 -> 5 | F34: =F30+F33+F32 -> 55 | G34: =G30+G33 -> -24
B36: Depreciation & Amoritzation | E36: =E25 -> -10 | F36: =F25 -> -96 | G36: =G25 -> -26
B37: EBITDA | E37: =E27-E36 -> 54 | F37: =F27-F36 -> 247 | G37: =G27-G36 -> 38
B39: Add: Equity-based compensation | E39: 0 | F39: 8 | G39: 3
B40: Add: Acquisition-related expenses | E40: 7 | F40: 1 | G40: 0
B41: Add: IPO-related expenses | E41: 0 | F41: 7 | G41: 6
B42: Add: Founder discretionary expenses | E42: =E45-E37-SUM(E39:E41)-SUM(E43:E44) -> 198 | F42: =F45-F37-SUM(F39:F41)-SUM(F43:F44) -> 25 | G42: 0
B43: Add: Area Director buyouts | E43: 2 | F43: 42 | G43: 32
B44: Add: Corporate transition & other | E44: 2 | F44: 9 | G44: 5
B45: Adjusted EBITDA | E45: 263 | F45: 339 | G45: =G37+SUM(G39:G44) -> 84
E46: =E45/E22 -> 0.40275651 | F46: =F45/F22 -> 0.46823204 | G46: =G45/G22 -> 0.45405405
B48: Note: 2025 splits Predecessor (pre-1/16/25) and Successor periods on different accounting bases (pushdown/purchase accounting); combined here.
B49: D&A and interest step up materially post-acquisition. FY2024 founder-discretionary add-back is a derived plug to the disclosed $263M
B50: (no line-item full-year 2024 recon in S-1).

Sheet LBO Entry
B2: ='Assumptions & Financials'!B2 -> Jersey Mike's Subs
B3: LBO Entry Valuation
B4: ($ Millions)
B6: Initial Valuation
B8: Enterprise Value | E8: ='Assumptions & Financials'!E8 -> 8000
B9: Less: Net debt | E9: =-'Assumptions & Financials'!E11 -> -1750
B10: Equity Purchase Price | E10: =SUM(E8:E9) -> 6250
B12: Entry LTM Adj. EBITDA (FY2024) | E12: ='Assumptions & Financials'!E9 -> 263
B13: Implied EV / LTM EBITDA | E13: =E8/E12 -> 30.418251
B15: Uses of Funds
B16: Buyout of equity | C16: =E10 -> 6250
B17: Fees (transaction & financing) | C17: =H24+H27 -> 105
B18: Total Uses | C18: =SUM(C16:C17) -> 6355
B20: Sources of Funds | F20: Fees
C21: EBITDA turns | D21: $ investment | G21: % fees | H21: Fee | I21: Term | J21: Fee / year
B22: Excess cash | C22: =D22/E12 -> 0 | D22: 0 | F22: Financing fees
B23: New Debt | C23: 2.85171 | D23: =C23*$E$12 -> 749.99973 | F23: =B23 -> New Debt | G23: 0.015 | H23: =D23*G23 -> 11.249996 | I23: 7 | J23: =IFERROR(G23*D23/I23, "NM") -> 1.6071423
B24: Rollover Equity | C24: 2.38 | D24: =C24*$E$12 -> 625.94 | F24: Financing fees | H24: =SUM(H23:H23) -> 11.249996 | J24: =SUM(J23:J23) -> 1.6071423
B25: Sponsor equity | C25: =D25/E12 -> 18.931788 | D25: =C18-SUM(D22:D24) -> 4979.0603
B26: Total Sources | C26: =SUM(C22:C25) -> 24.163498 | D26: =SUM(D22:D25) -> 6355 | G26: % of offer value | H26: Fee
F27: Trans. fees | G27: 0.015 | H27: =G27*E10 -> 93.75

Sheet LBO Exit
B2: ='LBO Entry'!B2 -> Jersey Mike's Subs
B3: LBO Exit Valuation
B4: ($ Millions)
B6: Exit Valuation
B8: Exit EBITDA | F8: =F10/F9 -> 387.09677
B9: EBITDA Multiple | F9: ='Assumptions & Financials'!E13 -> 31
B10: Enterprise Value | F10: ='Assumptions & Financials'!E12 -> 12000
B12: Less: Net Debt | F12: =-'Assumptions & Financials'!E15 -> -2100
B13: Exit Equity | F13: =F10+F12 -> 9900
B15: Sponsor's Equity at exit EBITDA multiple of: | G15: MOIC | H15: IRR | I15: ='Assumptions & Financials'!E10 -> 45673 | J15: ='Assumptions & Financials'!E14 -> 46295
B17: =B18-1 -> 28 | G17: =IFERROR((SUM(J17:J17)/-I17),"NM") -> 1.579583 | H17: =IFERROR(XIRR(I17:J17,$I$15:$J$15),0) -> 0.3076997 | I17: =-'LBO Entry'!$D$25 -> -4979.0603 | J17: =($F$8*B17+$F$12)*(1-'Assumptions & Financials'!$E$16) -> 7864.8387
B18: =B19-1 -> 29 | G18: =IFERROR((SUM(J18:J18)/-I18),"NM") -> 1.6495534 | H18: =IFERROR(XIRR(I18:J18,$I$15:$J$15),0) -> 0.34138741 | I18: =-'LBO Entry'!$D$25 -> -4979.0603 | J18: =($F$8*B18+$F$12)*(1-'Assumptions & Financials'!$E$16) -> 8213.2258
B19: =B20-1 -> 30 | G19: =IFERROR((SUM(J19:J19)/-I19),"NM") -> 1.7195239 | H19: =IFERROR(XIRR(I19:J19,$I$15:$J$15),0) -> 0.37448964 | I19: =-'LBO Entry'!$D$25 -> -4979.0603 | J19: =($F$8*B19+$F$12)*(1-'Assumptions & Financials'!$E$16) -> 8561.6129
B20: =F9 -> 31 | G20: =IFERROR((SUM(J20:J20)/-I20),"NM") -> 1.7894943 | H20: =IFERROR(XIRR(I20:J20,$I$15:$J$15),0) -> 0.40703979 | I20: =-'LBO Entry'!$D$25 -> -4979.0603 | J20: =($F$8*B20+$F$12)*(1-'Assumptions & Financials'!$E$16) -> 8910
B21: =B20+1 -> 32 | G21: =IFERROR((SUM(J21:J21)/-I21),"NM") -> 1.8594648 | H21: =IFERROR(XIRR(I21:J21,$I$15:$J$15),0) -> 0.43906813 | I21: =-'LBO Entry'!$D$25 -> -4979.0603 | J21: =($F$8*B21+$F$12)*(1-'Assumptions & Financials'!$E$16) -> 9258.3871
B22: =B21+1 -> 33 | G22: =IFERROR((SUM(J22:J22)/-I22),"NM") -> 1.9294352 | H22: =IFERROR(XIRR(I22:J22,$I$15:$J$15),0) -> 0.47060221 | I22: =-'LBO Entry'!$D$25 -> -4979.0603 | J22: =($F$8*B22+$F$12)*(1-'Assumptions & Financials'!$E$16) -> 9606.7742
B23: =B22+1 -> 34 | G23: =IFERROR((SUM(J23:J23)/-I23),"NM") -> 1.9994057 | H23: =IFERROR(XIRR(I23:J23,$I$15:$J$15),0) -> 0.50166718 | I23: =-'LBO Entry'!$D$25 -> -4979.0603 | J23: =($F$8*B23+$F$12)*(1-'Assumptions & Financials'!$E$16) -> 9955.1613
